[
  {
    "source_uri": "https://www.nytimes.com/2026/04/17/world/asia/myanmar-president-amnesty.html",
    "headline": "Myanmar Frees Ousted President, but Not Daw Aung San Suu Kyi",
    "primary_sentiment": "POSITIVE",
    "confidence_score": 0.9891,
    "published_at": "2026-04-20T01:18:05.615153+00:00"
  },
  {
    "source_uri": "https://www.nytimes.com/2026/04/17/world/middleeast/lebanon-hezbollah-ceasefire.html",
    "headline": "Why Lebanon\u2019s Government Has Struggled to Contain Hezbollah",
    "primary_sentiment": "NEGATIVE",
    "confidence_score": 0.9429,
    "published_at": "2026-04-20T01:18:05.603403+00:00"
  },
  {
    "source_uri": "https://www.nytimes.com/2026/04/17/world/middleeast/european-leaders-discuss-an-international-mission-to-restore-shipping-in-strait-of-hormuz.html",
    "headline": "Europe Wants to Help Restore Shipping in the Strait. It Just Isn\u2019t Sure How.",
    "primary_sentiment": "POSITIVE",
    "confidence_score": 0.788,
    "published_at": "2026-04-20T01:18:05.602159+00:00"
  },
  {
    "source_uri": "https://www.nytimes.com/2026/04/17/world/canada/trump-lutnick-canada-us-talks-trade-deal.html",
    "headline": "Lutnick Says Canada Trade Deal Needs to Be Reworked Ahead of Talks",
    "primary_sentiment": "NEGATIVE",
    "confidence_score": 0.9966,
    "published_at": "2026-04-20T01:18:05.600895+00:00"
  },
  {
    "source_uri": "https://www.nytimes.com/2026/04/17/business/mark-mobius-dead.html",
    "headline": "Mark Mobius, Pioneering Investor in Emerging Markets, Dies at 89",
    "primary_sentiment": "POSITIVE",
    "confidence_score": 0.9997,
    "published_at": "2026-04-20T01:18:05.598326+00:00"
  },
  {
    "source_uri": "https://www.nytimes.com/2026/04/17/world/europe/timmy-whale-stranded-rescue-germany.html",
    "headline": "Rescuers Try to Save Timmy, a Whale Stranded Off Germany",
    "primary_sentiment": "NEGATIVE",
    "confidence_score": 0.9988,
    "published_at": "2026-04-20T01:18:05.592846+00:00"
  },
  {
    "source_uri": "https://www.nytimes.com/2026/04/17/world/middleeast/trump-iran-hormuz-peace-deal.html",
    "headline": "Amid Conflicting Messages From Trump and Iran, Hopes for Peace Deal Emerge",
    "primary_sentiment": "NEGATIVE",
    "confidence_score": 0.9461,
    "published_at": "2026-04-20T01:18:05.578880+00:00"
  },
  {
    "source_uri": "https://www.nytimes.com/live/2026/04/17/world/iran-us-war-trump/iran-says-the-strait-of-hormuz-is-open-but-adds-that-it-is-still-under-tehrans-supervision",
    "headline": "Iran says the Strait of Hormuz is open, but adds that it is still under Tehran\u2019s supervision.",
    "primary_sentiment": "POSITIVE",
    "confidence_score": 0.9603,
    "published_at": "2026-04-20T01:18:05.577621+00:00"
  },
  {
    "source_uri": "https://www.nytimes.com/2026/04/17/health/hiv-testing-treatment-data-pepfar.html",
    "headline": "New PEPFAR Data Show Worrying Declines in Testing and Treatment for H.I.V.",
    "primary_sentiment": "POSITIVE",
    "confidence_score": 0.997,
    "published_at": "2026-04-20T01:18:05.575100+00:00"
  },
  {
    "source_uri": "https://www.nytimes.com/2026/04/18/world/europe/trump-pope-leo-iran.html",
    "headline": "A Mild-Mannered Pope Finds His Voice",
    "primary_sentiment": "NEGATIVE",
    "confidence_score": 0.9537,
    "published_at": "2026-04-20T01:18:05.572573+00:00"
  },
  {
    "source_uri": "https://www.nytimes.com/2026/04/18/world/canada/carney-poilievre-lewis-canada-politics.html",
    "headline": "Carney\u2019s Liberal Majority Reshapes Fortunes to the Left and the Right",
    "primary_sentiment": "POSITIVE",
    "confidence_score": 0.9994,
    "published_at": "2026-04-20T01:18:05.566308+00:00"
  },
  {
    "source_uri": "https://www.nytimes.com/2026/04/18/world/middleeast/iran-tanker-strait-of-hormuz.html",
    "headline": "Ships Attacked in Strait of Hormuz as Iran Declares Strict Control of Vital Shipping Route",
    "primary_sentiment": "POSITIVE",
    "confidence_score": 0.9841,
    "published_at": "2026-04-20T01:18:05.561218+00:00"
  },
  {
    "source_uri": "https://www.nytimes.com/2026/04/19/world/middleeast/us-iran-cease-fire-violations-strait-of-hormuz.html",
    "headline": "U.S. Attacks Iranian Cargo Ship as Both Countries Claim Cease-Fire Violations",
    "primary_sentiment": "NEGATIVE",
    "confidence_score": 0.9896,
    "published_at": "2026-04-20T01:18:05.556229+00:00"
  },
  {
    "source_uri": "https://www.nytimes.com/2026/04/18/world/africa/pope-news-media-trump-africa.html",
    "headline": "Pope Says News Outlets Misread Some of His Remarks as Criticism of Trump",
    "primary_sentiment": "NEGATIVE",
    "confidence_score": 0.9865,
    "published_at": "2026-04-20T01:18:05.547315+00:00"
  },
  {
    "source_uri": "https://www.nytimes.com/2026/04/18/world/europe/kyiv-ukraine-mass-shooting-hostages.html",
    "headline": "Kyiv Mass Shooting Kills 6 and Gunman Is Shot Dead After Taking Hostages in Grocery",
    "primary_sentiment": "NEGATIVE",
    "confidence_score": 0.8959,
    "published_at": "2026-04-20T01:18:05.544811+00:00"
  },
  {
    "source_uri": "https://www.nytimes.com/2026/04/19/world/middleeast/hamas-weapons-israel.html",
    "headline": "Hamas Officials Say Group Is Ready to Hand Over Some Weapons",
    "primary_sentiment": "NEGATIVE",
    "confidence_score": 0.9877,
    "published_at": "2026-04-20T01:18:05.533117+00:00"
  },
  {
    "source_uri": "https://www.bbc.com/news/videos/cly90z9g5q3o?at_medium=RSS&at_campaign=rss",
    "headline": "BBC reports from Lebanese border town as residents try to return home",
    "primary_sentiment": "NEGATIVE",
    "confidence_score": 0.9046,
    "published_at": "2026-04-20T01:18:05.354015+00:00"
  },
  {
    "source_uri": "https://www.bbc.com/news/videos/c4gjk99vp87o?at_medium=RSS&at_campaign=rss",
    "headline": "Drone footage shows huge Malaysian coastal village fire",
    "primary_sentiment": "NEGATIVE",
    "confidence_score": 0.9828,
    "published_at": "2026-04-20T01:18:05.350164+00:00"
  },
  {
    "source_uri": "https://www.bbc.com/news/articles/cy91r7ww3weo?at_medium=RSS&at_campaign=rss",
    "headline": "Australia's most-decorated soldier vows to fight war crime charges",
    "primary_sentiment": "POSITIVE",
    "confidence_score": 0.9424,
    "published_at": "2026-04-20T01:18:05.316047+00:00"
  },
  {
    "source_uri": "https://www.bbc.com/news/articles/c8ejn778j4do?at_medium=RSS&at_campaign=rss",
    "headline": "Ukraine police chief resigns after officers allegedly fled deadly shooting",
    "primary_sentiment": "NEGATIVE",
    "confidence_score": 0.9907,
    "published_at": "2026-04-20T01:18:05.304318+00:00"
  }
]